cerina/__init__.py
cerina/agents.py
cerina/gpt.py
cerina/optimiser.py
cerina/prompt_template.py
cerina/search.py
cerina/search_img.py
cerina/search_text.py
cerina/Agents/__init__.py
cerina/Agents/superagents.py
cerina/Scrapping/__init__.py
cerina/Scrapping/selenium_scrapper.py
cerina-0.2.8.dist-info/METADATA
cerina-0.2.8.dist-info/WHEEL
cerina-0.2.8.dist-info/top_level.txt
cerina-0.2.8.dist-info/RECORD
