Metadata-Version: 2.1
Name: cerina
Version: 0.2.8
Summary: Next-gen Sync & Async AI agents with 100+ functionalities
Requires-Dist: aiohttp
Requires-Dist: nest-asyncio
Requires-Dist: requests
Requires-Dist: pytest
Requires-Dist: webdriver-manager
Requires-Dist: selenium
